yamio/__init__.py
yamio/dolfin.py
yamio/helpers.py
yamio/hip.py
yamio/mesh.py
yamio/mesh_utils.py
yamio/tiny_3d_engine.py
yamio/ensight/__init__.py
yamio/ensight/gold.py
yamio/vis/__init__.py
yamio/vis/matplotlib.py
yamio/vis/pyvista.py
yamio-0.1.3.dist-info/LICENSE
yamio-0.1.3.dist-info/METADATA
yamio-0.1.3.dist-info/WHEEL
yamio-0.1.3.dist-info/top_level.txt
yamio-0.1.3.dist-info/RECORD
