Metadata-Version: 2.1
Name: yamio
Version: 0.1.3
Summary: A bridge between pyhip and meshio
Home-page: https://github.com/lpereira95/yamio
Author: L. F. Pereira
Author-email: luisfgpereira95@gmail.com
License: UNKNOWN
Project-URL: Homepage, https://github.com/lpereira95/yamio
Project-URL: Bug Tracker, https://github.com/lpereira95/yamio/issues
Keywords: mesh,file formats,scientific computing,finite elements
Platform: UNKNOWN
Classifier: Programming Language :: Python :: 3.6
Classifier: Programming Language :: Python :: 3.7
Classifier: Programming Language :: Python :: 3.8
Classifier: Programming Language :: Python :: 3.9
Classifier: License :: OSI Approved :: MIT License
Classifier: Topic :: Scientific/Engineering
Requires-Python: >=3.7
Provides-Extra: vis
License-File: LICENSE
